dummit/__init__.py
dummit/df_tests.py
dummit/dummit.py
dummit/factories.py
dummit/inputs.py
dummit/locations.py
dummit/secrets.py
dummit/tests.py
dummit-0.0.5.dev1.dist-info/LICENSE
dummit-0.0.5.dev1.dist-info/METADATA
dummit-0.0.5.dev1.dist-info/WHEEL
dummit-0.0.5.dev1.dist-info/top_level.txt
dummit-0.0.5.dev1.dist-info/RECORD
