Metadata-Version: 2.1
Name: dummit
Version: 0.0.5.dev1
Summary: Dummy Input Tests: data quality checks
Home-page: https://github.com/Piotr12/dummit
Author: Pan Piotrek
License: UNKNOWN
Project-URL: Bug Tracker, https://github.com/Piotr12/dummit/issues
Platform: UNKNOWN
Classifier: Programming Language :: Python :: 3
Classifier: License :: OSI Approved :: MIT License
Classifier: Operating System :: OS Independent
Requires-Python: >=3.6
License-File: LICENSE
Requires-Dist: pyyaml
Requires-Dist: azure-keyvault-secrets
Requires-Dist: azure-identity
Requires-Dist: pandas
Requires-Dist: azure-storage-blob
